{
  "generatedAt": "2026-05-23T17:45:15.516Z",
  "source": "tools/monitor-spoilers/monitor.js",
  "spoilers": [
    {
      "id": "3f7856dec50a7605073b614a3f0e948b161a087b185e599383bf26add6245ab2",
      "anime": "blackclover",
      "handle": "pacemanop",
      "sourceLabel": "Black Clover",
      "title": "Black Clover Vol 38 Cover Illustration #BlackClover #BCSpoiler",
      "text": "Black Clover Vol 38 Cover Illustration #BlackClover #BCSpoiler",
      "url": "https://nitter.net/PacemanOP/status/2058043594687361229#m",
      "date": "Sat, 23 May 2026 04:33:24 GMT",
      "isSpoiler": true,
      "hasAttachments": true,
      "attachments": [
        "https://nitter.net/pic/media%2FHI-jviTbcAAL-Ej.jpg"
      ]
    },
    {
      "id": "77244280bf0f99213538c3ab99bf9acb5e0ac16b21ae73454c3fd840a3e5ab85",
      "anime": "blackclover",
      "handle": "pacemanop",
      "sourceLabel": "Black Clover",
      "title": "#10 SB #BlackClover #BCSpoilers Video",
      "text": "#10 SB #BlackClover #BCSpoilers Video",
      "url": "https://nitter.net/PacemanOP/status/2054549956523077750#m",
      "date": "Wed, 13 May 2026 13:10:55 GMT",
      "isSpoiler": true,
      "hasAttachments": true,
      "attachments": [
        "https://nitter.net/pic/ext_tw_video_thumb%2F2054549935920705536%2Fpu%2Fimg%2FTS4vTWND0acKl05I.jpg"
      ]
    }
  ],
  "misc": [
    {
      "id": "24b60c3459741e3241ac7cf5f830f6e191f9183790848594f04528f641cb83fd",
      "anime": "onepiece",
      "handle": "mugiwara_23",
      "sourceLabel": "One Piece γ",
      "title": "The 2nd Global ONE PIECE Character Popularity Contest I voted for “MONKEY D. LUFFY”! onepiecewt100-2026.com/en/vo… #ONEPIECE #ONEPIECE_WT100",
      "text": "The 2nd Global ONE PIECE Character Popularity Contest I voted for “MONKEY D. LUFFY”! onepiecewt100-2026.com/en/vo… #ONEPIECE #ONEPIECE_WT100",
      "url": "https://nitter.net/Mugiwara_23/status/2058216065163751756#m",
      "date": "Sat, 23 May 2026 15:58:44 GMT",
      "isSpoiler": false,
      "hasAttachments": true,
      "attachments": [
        "https://nitter.net/pic/card_img%2F2056650054534918144%2FKDiGdVNK%3Fformat%3Djpg%26name%3D800x419"
      ]
    },
    {
      "id": "6138e04b2a0eb7e51f4248dc1cd56c77fc4bf0380574404fa32a0cfe3d0eeace",
      "anime": "onepiece",
      "handle": "mugiwara_23",
      "sourceLabel": "One Piece γ",
      "title": "🪭━━━━━━━━━━━━ TVアニメ『あかね噺』 ノンクレジットエンディング映像 ━━━━━━━━━━━━🪭 ▮エンディング主題歌 桑田佳祐 「AKANE On My Mind～饅頭こわい」 piped.video/wacbFJzImfk #あかね噺 #桑田佳祐 Video",
      "text": "🪭━━━━━━━━━━━━ TVアニメ『あかね噺』 ノンクレジットエンディング映像 ━━━━━━━━━━━━🪭 ▮エンディング主題歌 桑田佳祐 「AKANE On My Mind～饅頭こわい」 piped.video/wacbFJzImfk #あかね噺 #桑田佳祐 Video",
      "url": "https://nitter.net/akanebanashi_PR/status/2058200277002637608#m",
      "date": "Sat, 23 May 2026 14:56:00 GMT",
      "isSpoiler": false,
      "hasAttachments": true,
      "attachments": [
        "https://nitter.net/pic/media%2FHFjujWLXgAEG6Yy.jpg"
      ]
    },
    {
      "id": "5074a2a4ab8ae7de07288449181094fedb0af404331bdc72b375899327cf89b6",
      "anime": "onepiece",
      "handle": "mugiwara_23",
      "sourceLabel": "One Piece γ",
      "title": "HAPPY BIRTHDAY🎉 今日は「キャロット」の誕生日！ #キャロット誕生祭2026 #海賊無双4 #ONEPIECEODYSSEY #ONEPIECE",
      "text": "HAPPY BIRTHDAY🎉 今日は「キャロット」の誕生日！ #キャロット誕生祭2026 #海賊無双4 #ONEPIECEODYSSEY #ONEPIECE",
      "url": "https://nitter.net/opgame_official/status/2058201286105858164#m",
      "date": "Sat, 23 May 2026 15:00:00 GMT",
      "isSpoiler": false,
      "hasAttachments": true,
      "attachments": [
        "https://nitter.net/pic/media%2FHF_l5zMbcAAdL59.jpg"
      ]
    },
    {
      "id": "bc4a7d8c68ee4da6f3baa3be2fa5876c1230b14658d6344a3ed78a577c5cfbf4",
      "anime": "onepiece",
      "handle": "mugiwara_23",
      "sourceLabel": "One Piece γ",
      "title": "HAPPY BIRTHDAY🎉 今日は「キャロット」の誕生日！ #キャロット誕生祭2026 #ワンピカード #ONEPIECEカードゲーム",
      "text": "HAPPY BIRTHDAY🎉 今日は「キャロット」の誕生日！ #キャロット誕生祭2026 #ワンピカード #ONEPIECEカードゲーム",
      "url": "https://nitter.net/ONEPIECE_tcg/status/2058201288739840506#m",
      "date": "Sat, 23 May 2026 15:00:01 GMT",
      "isSpoiler": false,
      "hasAttachments": true,
      "attachments": [
        "https://nitter.net/pic/media%2FHHI0ap3aAAAunz4.jpg"
      ]
    },
    {
      "id": "2a154942cacc49afcc19f5c4320cadd7457656f68abe10eac13579c36d8b36d9",
      "anime": "onepiece",
      "handle": "mugiwara_23",
      "sourceLabel": "One Piece γ",
      "title": "5月24日はキャロットの誕生日 HAPPY BIRTHDAY CARROT #キャロット誕生祭2026 #CARROTbirthday2026",
      "text": "5月24日はキャロットの誕生日 HAPPY BIRTHDAY CARROT #キャロット誕生祭2026 #CARROTbirthday2026",
      "url": "https://nitter.net/onepiece_DVD/status/2058201294532137281#m",
      "date": "Sat, 23 May 2026 15:00:02 GMT",
      "isSpoiler": false,
      "hasAttachments": true,
      "attachments": [
        "https://nitter.net/pic/media%2FHGE-Zx2b0AAoOMQ.jpg"
      ]
    },
    {
      "id": "6678299d3623f7fee08e0ec65c32e49afece4793a52ebabef38b206bc3c725d4",
      "anime": "onepiece",
      "handle": "mugiwara_23",
      "sourceLabel": "One Piece γ",
      "title": "5.24 HAPPY BIRTHDAY CARROT #キャロット誕生祭2026 #ONEPIECE",
      "text": "5.24 HAPPY BIRTHDAY CARROT #キャロット誕生祭2026 #ONEPIECE",
      "url": "https://nitter.net/Eiichiro_Staff/status/2058201317986951205#m",
      "date": "Sat, 23 May 2026 15:00:08 GMT",
      "isSpoiler": false,
      "hasAttachments": true,
      "attachments": [
        "https://nitter.net/pic/media%2FHJAzL7gbIAAFxIP.jpg"
      ]
    },
    {
      "id": "8217d4096eda29e30c5d140a628a9f5a46a5c54a4de9288f2a2d165955a57dda",
      "anime": "boruto",
      "handle": "schmurfiv1",
      "sourceLabel": "Boruto",
      "title": "I actually forgot that this irrelevant character actually died lmao. Now Ikemoto has to start killing off the main side cast (Rest in Peace Shikadai) #BORUTO daily yodo (@yododaily) — https://nitter.n",
      "text": "I actually forgot that this irrelevant character actually died lmao. Now Ikemoto has to start killing off the main side cast (Rest in Peace Shikadai) #BORUTO daily yodo (@yododaily) — https://nitter.net/yododaily/status/1924846298768752859#m",
      "url": "https://nitter.net/SchmurfiV1/status/2057523879719862618#m",
      "date": "Thu, 21 May 2026 18:08:14 GMT",
      "isSpoiler": false,
      "hasAttachments": true,
      "attachments": [
        "https://nitter.net/pic/media%2FGrZtbrJXoAACXnN.jpg",
        "https://nitter.net/pic/media%2FGrZtefnXoAAx6oM.jpg"
      ]
    },
    {
      "id": "0330271efe66a0db1f0efa8bb98e5569681d7c0db6f83809e2ff9c2ec6ea81bb",
      "anime": "boruto",
      "handle": "schmurfiv1",
      "sourceLabel": "Boruto",
      "title": "Sumire to Boruto whenever Sarada isn’t around: #BORUTO",
      "text": "Sumire to Boruto whenever Sarada isn’t around: #BORUTO",
      "url": "https://nitter.net/SchmurfiV1/status/2057497724669300829#m",
      "date": "Thu, 21 May 2026 16:24:18 GMT",
      "isSpoiler": false,
      "hasAttachments": true,
      "attachments": [
        "https://nitter.net/pic/media%2FHI2zRlDWIAEuUZB.jpg"
      ]
    },
    {
      "id": "9df9ce1466977f1d546d3ba3ee6dca476798641c88cf9dc1dbc6dc69cbfc4f18",
      "anime": "boruto",
      "handle": "schmurfiv1",
      "sourceLabel": "Boruto",
      "title": "Ikemoto really has to slap his meat and slam his balls on the table and start putting some emotions into the story or instead Boruto TBV won’t get any huge reactions from outside the Manga fanbase… An",
      "text": "Ikemoto really has to slap his meat and slam his balls on the table and start putting some emotions into the story or instead Boruto TBV won’t get any huge reactions from outside the Manga fanbase… And I don’t think that this is his or Kishimoto’s goal for Boruto TBV…🤷🏻‍♂️",
      "url": "https://nitter.net/SchmurfiV1/status/2057394490726338845#m",
      "date": "Thu, 21 May 2026 09:34:05 GMT",
      "isSpoiler": false,
      "hasAttachments": false,
      "attachments": []
    },
    {
      "id": "6d129494692532daea7ee7701916ab27c9f7b66609a236264cc4668f4e2054ef",
      "anime": "boruto",
      "handle": "schmurfiv1",
      "sourceLabel": "Boruto",
      "title": "You would think every child there is the son or daughter of Goku, Vegeta or Saber? But instead those are children of some random characters we don’t know (Sumire and her parents) and fucking InoShikaC",
      "text": "You would think every child there is the son or daughter of Goku, Vegeta or Saber? But instead those are children of some random characters we don’t know (Sumire and her parents) and fucking InoShikaCho😭😭",
      "url": "https://nitter.net/SchmurfiV1/status/2057394488184623244#m",
      "date": "Thu, 21 May 2026 09:34:05 GMT",
      "isSpoiler": false,
      "hasAttachments": false,
      "attachments": []
    },
    {
      "id": "f90ed245a19161bf0e453e207981ccd46dd2bf97663d5a7cfc1613a4adad3baa",
      "anime": "boruto",
      "handle": "schmurfiv1",
      "sourceLabel": "Boruto",
      "title": "And don’t get me started on the Disney writing… They fought several threats which should be at least at the higher peak of Shippuden (Jura is even stronger than Madara, Hashirama, Kaguya etc.) And… no",
      "text": "And don’t get me started on the Disney writing… They fought several threats which should be at least at the higher peak of Shippuden (Jura is even stronger than Madara, Hashirama, Kaguya etc.) And… nobody dies? Or at least no one even suffers a major injury??",
      "url": "https://nitter.net/SchmurfiV1/status/2057394484325781648#m",
      "date": "Thu, 21 May 2026 09:34:04 GMT",
      "isSpoiler": false,
      "hasAttachments": false,
      "attachments": []
    },
    {
      "id": "42cd36212b796d7f16b5ae2eff31b8bf9e8de386d0b054989d98e894d4825f97",
      "anime": "boruto",
      "handle": "schmurfiv1",
      "sourceLabel": "Boruto",
      "title": "It doesn’t feel like an emotional, dark and suffering fate for Boruto right now… Nobody dies (Except Sasuke, Naruto and Hinata being sealed). Boruto is viewed as a traitor and killer for exact… hmm… 6",
      "text": "It doesn’t feel like an emotional, dark and suffering fate for Boruto right now… Nobody dies (Except Sasuke, Naruto and Hinata being sealed). Boruto is viewed as a traitor and killer for exact… hmm… 6 chapters? After that everyone starts to suddenly trust him?",
      "url": "https://nitter.net/SchmurfiV1/status/2057394481406542119#m",
      "date": "Thu, 21 May 2026 09:34:03 GMT",
      "isSpoiler": false,
      "hasAttachments": false,
      "attachments": []
    },
    {
      "id": "e7de4abcdaf9bc5153e3822f95b8a9b353dc87c1c355e7a56a5d5337fcb778f2",
      "anime": "blackclover",
      "handle": "pacemanop",
      "sourceLabel": "Black Clover",
      "title": "YOOOOOOOOOOOOOOOO",
      "text": "YOOOOOOOOOOOOOOOO",
      "url": "https://nitter.net/d0nut2x/status/2058117171083870236#m",
      "date": "Sat, 23 May 2026 09:25:46 GMT",
      "isSpoiler": false,
      "hasAttachments": true,
      "attachments": [
        "https://nitter.net/pic/media%2FHI_mpGeWEAArDrY.jpg"
      ]
    },
    {
      "id": "0b97d24236b0319393ef0410cf5066500eeebdbf7d2585409c4c2502c1fb80cc",
      "anime": "blackclover",
      "handle": "pacemanop",
      "sourceLabel": "Black Clover",
      "title": "Devil May Cry S2 remaining 4 EP titles and Length The Garden of Deadly Sins — 31m Purgatorio — 37m Into the City of Woe — 35m Vexilla Regis Prodeunt Inferni — 31m #Devilmaycry Pace (@PacemanOP) Devil ",
      "text": "Devil May Cry S2 remaining 4 EP titles and Length The Garden of Deadly Sins — 31m Purgatorio — 37m Into the City of Woe — 35m Vexilla Regis Prodeunt Inferni — 31m #Devilmaycry Pace (@PacemanOP) Devil May Cry S2 first 4 EP titles and length The Fallen — 37m Shades — 31m The Panther, The Lion, The Wolf — 29m A Pit of Serpents — 37m #devilmaycry — https://nitter.net/PacemanOP/status/2050472148855361852#m",
      "url": "https://nitter.net/PacemanOP/status/2053539680214503638#m",
      "date": "Sun, 10 May 2026 18:16:27 GMT",
      "isSpoiler": false,
      "hasAttachments": false,
      "attachments": []
    },
    {
      "id": "3f7e9ad6f81ba75a83d805e547b1ac1fdea346014b9a26d12e88acc92bfe5063",
      "anime": "blackclover",
      "handle": "pacemanop",
      "sourceLabel": "Black Clover",
      "title": "Found him. Please report and block this sick mf. 𝑯𝒊𝒌𝒂𝒓𝒊 𝑺𝒖𝒛𝒖𝒌𝒊 ♣️🍀♦️❤️♠️🌕 (@HikariSuzuki14) There’s an account that attached my pfp to a video of a women being graped and beheaded. Unfor",
      "text": "Found him. Please report and block this sick mf. 𝑯𝒊𝒌𝒂𝒓𝒊 𝑺𝒖𝒛𝒖𝒌𝒊 ♣️🍀♦️❤️♠️🌕 (@HikariSuzuki14) There’s an account that attached my pfp to a video of a women being graped and beheaded. Unfortunately I cannot find the account. If you encounter the account please block and report it immediately! — https://nitter.net/HikariSuzuki14/status/2052749375114252633#m",
      "url": "https://nitter.net/HikariSuzuki14/status/2052800940558749974#m",
      "date": "Fri, 08 May 2026 17:20:58 GMT",
      "isSpoiler": false,
      "hasAttachments": true,
      "attachments": [
        "https://nitter.net/pic/media%2FHH0DkEkXYAMW1ng.jpg",
        "https://nitter.net/pic/media%2FHH0Dkk1XwAIstmq.jpg",
        "https://nitter.net/pic/media%2FHH0Dk75XoAA79sG.jpg"
      ]
    },
    {
      "id": "ca264c0c56ecb098854e71473cbc1ab05bc4a4c2c7afcad158bf61d7dd61c5b0",
      "anime": "blackclover",
      "handle": "pacemanop",
      "sourceLabel": "Black Clover",
      "title": "#SD258 #SAKAMOTODAYS258 suzuki fucking delivered this chapter I’m really really convinced this fight has been a big upscale from gozu vs shishiba and it seems like tenkyu is still the same as before. ",
      "text": "#SD258 #SAKAMOTODAYS258 suzuki fucking delivered this chapter I’m really really convinced this fight has been a big upscale from gozu vs shishiba and it seems like tenkyu is still the same as before. the choreography just went straight up at the end thanks suzuki ; )",
      "url": "https://nitter.net/OkizemeSD/status/2052613004118618258#m",
      "date": "Fri, 08 May 2026 04:54:10 GMT",
      "isSpoiler": false,
      "hasAttachments": true,
      "attachments": [
        "https://nitter.net/pic/media%2FHHxYphnWIAIsWc3.jpg"
      ]
    }
  ],
  "items": [
    {
      "id": "3f7856dec50a7605073b614a3f0e948b161a087b185e599383bf26add6245ab2",
      "anime": "blackclover",
      "handle": "pacemanop",
      "sourceLabel": "Black Clover",
      "title": "Black Clover Vol 38 Cover Illustration #BlackClover #BCSpoiler",
      "text": "Black Clover Vol 38 Cover Illustration #BlackClover #BCSpoiler",
      "url": "https://nitter.net/PacemanOP/status/2058043594687361229#m",
      "date": "Sat, 23 May 2026 04:33:24 GMT",
      "isSpoiler": true,
      "hasAttachments": true,
      "attachments": [
        "https://nitter.net/pic/media%2FHI-jviTbcAAL-Ej.jpg"
      ]
    },
    {
      "id": "77244280bf0f99213538c3ab99bf9acb5e0ac16b21ae73454c3fd840a3e5ab85",
      "anime": "blackclover",
      "handle": "pacemanop",
      "sourceLabel": "Black Clover",
      "title": "#10 SB #BlackClover #BCSpoilers Video",
      "text": "#10 SB #BlackClover #BCSpoilers Video",
      "url": "https://nitter.net/PacemanOP/status/2054549956523077750#m",
      "date": "Wed, 13 May 2026 13:10:55 GMT",
      "isSpoiler": true,
      "hasAttachments": true,
      "attachments": [
        "https://nitter.net/pic/ext_tw_video_thumb%2F2054549935920705536%2Fpu%2Fimg%2FTS4vTWND0acKl05I.jpg"
      ]
    },
    {
      "id": "24b60c3459741e3241ac7cf5f830f6e191f9183790848594f04528f641cb83fd",
      "anime": "onepiece",
      "handle": "mugiwara_23",
      "sourceLabel": "One Piece γ",
      "title": "The 2nd Global ONE PIECE Character Popularity Contest I voted for “MONKEY D. LUFFY”! onepiecewt100-2026.com/en/vo… #ONEPIECE #ONEPIECE_WT100",
      "text": "The 2nd Global ONE PIECE Character Popularity Contest I voted for “MONKEY D. LUFFY”! onepiecewt100-2026.com/en/vo… #ONEPIECE #ONEPIECE_WT100",
      "url": "https://nitter.net/Mugiwara_23/status/2058216065163751756#m",
      "date": "Sat, 23 May 2026 15:58:44 GMT",
      "isSpoiler": false,
      "hasAttachments": true,
      "attachments": [
        "https://nitter.net/pic/card_img%2F2056650054534918144%2FKDiGdVNK%3Fformat%3Djpg%26name%3D800x419"
      ]
    },
    {
      "id": "6138e04b2a0eb7e51f4248dc1cd56c77fc4bf0380574404fa32a0cfe3d0eeace",
      "anime": "onepiece",
      "handle": "mugiwara_23",
      "sourceLabel": "One Piece γ",
      "title": "🪭━━━━━━━━━━━━ TVアニメ『あかね噺』 ノンクレジットエンディング映像 ━━━━━━━━━━━━🪭 ▮エンディング主題歌 桑田佳祐 「AKANE On My Mind～饅頭こわい」 piped.video/wacbFJzImfk #あかね噺 #桑田佳祐 Video",
      "text": "🪭━━━━━━━━━━━━ TVアニメ『あかね噺』 ノンクレジットエンディング映像 ━━━━━━━━━━━━🪭 ▮エンディング主題歌 桑田佳祐 「AKANE On My Mind～饅頭こわい」 piped.video/wacbFJzImfk #あかね噺 #桑田佳祐 Video",
      "url": "https://nitter.net/akanebanashi_PR/status/2058200277002637608#m",
      "date": "Sat, 23 May 2026 14:56:00 GMT",
      "isSpoiler": false,
      "hasAttachments": true,
      "attachments": [
        "https://nitter.net/pic/media%2FHFjujWLXgAEG6Yy.jpg"
      ]
    },
    {
      "id": "5074a2a4ab8ae7de07288449181094fedb0af404331bdc72b375899327cf89b6",
      "anime": "onepiece",
      "handle": "mugiwara_23",
      "sourceLabel": "One Piece γ",
      "title": "HAPPY BIRTHDAY🎉 今日は「キャロット」の誕生日！ #キャロット誕生祭2026 #海賊無双4 #ONEPIECEODYSSEY #ONEPIECE",
      "text": "HAPPY BIRTHDAY🎉 今日は「キャロット」の誕生日！ #キャロット誕生祭2026 #海賊無双4 #ONEPIECEODYSSEY #ONEPIECE",
      "url": "https://nitter.net/opgame_official/status/2058201286105858164#m",
      "date": "Sat, 23 May 2026 15:00:00 GMT",
      "isSpoiler": false,
      "hasAttachments": true,
      "attachments": [
        "https://nitter.net/pic/media%2FHF_l5zMbcAAdL59.jpg"
      ]
    },
    {
      "id": "bc4a7d8c68ee4da6f3baa3be2fa5876c1230b14658d6344a3ed78a577c5cfbf4",
      "anime": "onepiece",
      "handle": "mugiwara_23",
      "sourceLabel": "One Piece γ",
      "title": "HAPPY BIRTHDAY🎉 今日は「キャロット」の誕生日！ #キャロット誕生祭2026 #ワンピカード #ONEPIECEカードゲーム",
      "text": "HAPPY BIRTHDAY🎉 今日は「キャロット」の誕生日！ #キャロット誕生祭2026 #ワンピカード #ONEPIECEカードゲーム",
      "url": "https://nitter.net/ONEPIECE_tcg/status/2058201288739840506#m",
      "date": "Sat, 23 May 2026 15:00:01 GMT",
      "isSpoiler": false,
      "hasAttachments": true,
      "attachments": [
        "https://nitter.net/pic/media%2FHHI0ap3aAAAunz4.jpg"
      ]
    },
    {
      "id": "2a154942cacc49afcc19f5c4320cadd7457656f68abe10eac13579c36d8b36d9",
      "anime": "onepiece",
      "handle": "mugiwara_23",
      "sourceLabel": "One Piece γ",
      "title": "5月24日はキャロットの誕生日 HAPPY BIRTHDAY CARROT #キャロット誕生祭2026 #CARROTbirthday2026",
      "text": "5月24日はキャロットの誕生日 HAPPY BIRTHDAY CARROT #キャロット誕生祭2026 #CARROTbirthday2026",
      "url": "https://nitter.net/onepiece_DVD/status/2058201294532137281#m",
      "date": "Sat, 23 May 2026 15:00:02 GMT",
      "isSpoiler": false,
      "hasAttachments": true,
      "attachments": [
        "https://nitter.net/pic/media%2FHGE-Zx2b0AAoOMQ.jpg"
      ]
    },
    {
      "id": "6678299d3623f7fee08e0ec65c32e49afece4793a52ebabef38b206bc3c725d4",
      "anime": "onepiece",
      "handle": "mugiwara_23",
      "sourceLabel": "One Piece γ",
      "title": "5.24 HAPPY BIRTHDAY CARROT #キャロット誕生祭2026 #ONEPIECE",
      "text": "5.24 HAPPY BIRTHDAY CARROT #キャロット誕生祭2026 #ONEPIECE",
      "url": "https://nitter.net/Eiichiro_Staff/status/2058201317986951205#m",
      "date": "Sat, 23 May 2026 15:00:08 GMT",
      "isSpoiler": false,
      "hasAttachments": true,
      "attachments": [
        "https://nitter.net/pic/media%2FHJAzL7gbIAAFxIP.jpg"
      ]
    },
    {
      "id": "8217d4096eda29e30c5d140a628a9f5a46a5c54a4de9288f2a2d165955a57dda",
      "anime": "boruto",
      "handle": "schmurfiv1",
      "sourceLabel": "Boruto",
      "title": "I actually forgot that this irrelevant character actually died lmao. Now Ikemoto has to start killing off the main side cast (Rest in Peace Shikadai) #BORUTO daily yodo (@yododaily) — https://nitter.n",
      "text": "I actually forgot that this irrelevant character actually died lmao. Now Ikemoto has to start killing off the main side cast (Rest in Peace Shikadai) #BORUTO daily yodo (@yododaily) — https://nitter.net/yododaily/status/1924846298768752859#m",
      "url": "https://nitter.net/SchmurfiV1/status/2057523879719862618#m",
      "date": "Thu, 21 May 2026 18:08:14 GMT",
      "isSpoiler": false,
      "hasAttachments": true,
      "attachments": [
        "https://nitter.net/pic/media%2FGrZtbrJXoAACXnN.jpg",
        "https://nitter.net/pic/media%2FGrZtefnXoAAx6oM.jpg"
      ]
    },
    {
      "id": "0330271efe66a0db1f0efa8bb98e5569681d7c0db6f83809e2ff9c2ec6ea81bb",
      "anime": "boruto",
      "handle": "schmurfiv1",
      "sourceLabel": "Boruto",
      "title": "Sumire to Boruto whenever Sarada isn’t around: #BORUTO",
      "text": "Sumire to Boruto whenever Sarada isn’t around: #BORUTO",
      "url": "https://nitter.net/SchmurfiV1/status/2057497724669300829#m",
      "date": "Thu, 21 May 2026 16:24:18 GMT",
      "isSpoiler": false,
      "hasAttachments": true,
      "attachments": [
        "https://nitter.net/pic/media%2FHI2zRlDWIAEuUZB.jpg"
      ]
    },
    {
      "id": "9df9ce1466977f1d546d3ba3ee6dca476798641c88cf9dc1dbc6dc69cbfc4f18",
      "anime": "boruto",
      "handle": "schmurfiv1",
      "sourceLabel": "Boruto",
      "title": "Ikemoto really has to slap his meat and slam his balls on the table and start putting some emotions into the story or instead Boruto TBV won’t get any huge reactions from outside the Manga fanbase… An",
      "text": "Ikemoto really has to slap his meat and slam his balls on the table and start putting some emotions into the story or instead Boruto TBV won’t get any huge reactions from outside the Manga fanbase… And I don’t think that this is his or Kishimoto’s goal for Boruto TBV…🤷🏻‍♂️",
      "url": "https://nitter.net/SchmurfiV1/status/2057394490726338845#m",
      "date": "Thu, 21 May 2026 09:34:05 GMT",
      "isSpoiler": false,
      "hasAttachments": false,
      "attachments": []
    },
    {
      "id": "6d129494692532daea7ee7701916ab27c9f7b66609a236264cc4668f4e2054ef",
      "anime": "boruto",
      "handle": "schmurfiv1",
      "sourceLabel": "Boruto",
      "title": "You would think every child there is the son or daughter of Goku, Vegeta or Saber? But instead those are children of some random characters we don’t know (Sumire and her parents) and fucking InoShikaC",
      "text": "You would think every child there is the son or daughter of Goku, Vegeta or Saber? But instead those are children of some random characters we don’t know (Sumire and her parents) and fucking InoShikaCho😭😭",
      "url": "https://nitter.net/SchmurfiV1/status/2057394488184623244#m",
      "date": "Thu, 21 May 2026 09:34:05 GMT",
      "isSpoiler": false,
      "hasAttachments": false,
      "attachments": []
    },
    {
      "id": "f90ed245a19161bf0e453e207981ccd46dd2bf97663d5a7cfc1613a4adad3baa",
      "anime": "boruto",
      "handle": "schmurfiv1",
      "sourceLabel": "Boruto",
      "title": "And don’t get me started on the Disney writing… They fought several threats which should be at least at the higher peak of Shippuden (Jura is even stronger than Madara, Hashirama, Kaguya etc.) And… no",
      "text": "And don’t get me started on the Disney writing… They fought several threats which should be at least at the higher peak of Shippuden (Jura is even stronger than Madara, Hashirama, Kaguya etc.) And… nobody dies? Or at least no one even suffers a major injury??",
      "url": "https://nitter.net/SchmurfiV1/status/2057394484325781648#m",
      "date": "Thu, 21 May 2026 09:34:04 GMT",
      "isSpoiler": false,
      "hasAttachments": false,
      "attachments": []
    },
    {
      "id": "42cd36212b796d7f16b5ae2eff31b8bf9e8de386d0b054989d98e894d4825f97",
      "anime": "boruto",
      "handle": "schmurfiv1",
      "sourceLabel": "Boruto",
      "title": "It doesn’t feel like an emotional, dark and suffering fate for Boruto right now… Nobody dies (Except Sasuke, Naruto and Hinata being sealed). Boruto is viewed as a traitor and killer for exact… hmm… 6",
      "text": "It doesn’t feel like an emotional, dark and suffering fate for Boruto right now… Nobody dies (Except Sasuke, Naruto and Hinata being sealed). Boruto is viewed as a traitor and killer for exact… hmm… 6 chapters? After that everyone starts to suddenly trust him?",
      "url": "https://nitter.net/SchmurfiV1/status/2057394481406542119#m",
      "date": "Thu, 21 May 2026 09:34:03 GMT",
      "isSpoiler": false,
      "hasAttachments": false,
      "attachments": []
    },
    {
      "id": "e7de4abcdaf9bc5153e3822f95b8a9b353dc87c1c355e7a56a5d5337fcb778f2",
      "anime": "blackclover",
      "handle": "pacemanop",
      "sourceLabel": "Black Clover",
      "title": "YOOOOOOOOOOOOOOOO",
      "text": "YOOOOOOOOOOOOOOOO",
      "url": "https://nitter.net/d0nut2x/status/2058117171083870236#m",
      "date": "Sat, 23 May 2026 09:25:46 GMT",
      "isSpoiler": false,
      "hasAttachments": true,
      "attachments": [
        "https://nitter.net/pic/media%2FHI_mpGeWEAArDrY.jpg"
      ]
    },
    {
      "id": "0b97d24236b0319393ef0410cf5066500eeebdbf7d2585409c4c2502c1fb80cc",
      "anime": "blackclover",
      "handle": "pacemanop",
      "sourceLabel": "Black Clover",
      "title": "Devil May Cry S2 remaining 4 EP titles and Length The Garden of Deadly Sins — 31m Purgatorio — 37m Into the City of Woe — 35m Vexilla Regis Prodeunt Inferni — 31m #Devilmaycry Pace (@PacemanOP) Devil ",
      "text": "Devil May Cry S2 remaining 4 EP titles and Length The Garden of Deadly Sins — 31m Purgatorio — 37m Into the City of Woe — 35m Vexilla Regis Prodeunt Inferni — 31m #Devilmaycry Pace (@PacemanOP) Devil May Cry S2 first 4 EP titles and length The Fallen — 37m Shades — 31m The Panther, The Lion, The Wolf — 29m A Pit of Serpents — 37m #devilmaycry — https://nitter.net/PacemanOP/status/2050472148855361852#m",
      "url": "https://nitter.net/PacemanOP/status/2053539680214503638#m",
      "date": "Sun, 10 May 2026 18:16:27 GMT",
      "isSpoiler": false,
      "hasAttachments": false,
      "attachments": []
    },
    {
      "id": "3f7e9ad6f81ba75a83d805e547b1ac1fdea346014b9a26d12e88acc92bfe5063",
      "anime": "blackclover",
      "handle": "pacemanop",
      "sourceLabel": "Black Clover",
      "title": "Found him. Please report and block this sick mf. 𝑯𝒊𝒌𝒂𝒓𝒊 𝑺𝒖𝒛𝒖𝒌𝒊 ♣️🍀♦️❤️♠️🌕 (@HikariSuzuki14) There’s an account that attached my pfp to a video of a women being graped and beheaded. Unfor",
      "text": "Found him. Please report and block this sick mf. 𝑯𝒊𝒌𝒂𝒓𝒊 𝑺𝒖𝒛𝒖𝒌𝒊 ♣️🍀♦️❤️♠️🌕 (@HikariSuzuki14) There’s an account that attached my pfp to a video of a women being graped and beheaded. Unfortunately I cannot find the account. If you encounter the account please block and report it immediately! — https://nitter.net/HikariSuzuki14/status/2052749375114252633#m",
      "url": "https://nitter.net/HikariSuzuki14/status/2052800940558749974#m",
      "date": "Fri, 08 May 2026 17:20:58 GMT",
      "isSpoiler": false,
      "hasAttachments": true,
      "attachments": [
        "https://nitter.net/pic/media%2FHH0DkEkXYAMW1ng.jpg",
        "https://nitter.net/pic/media%2FHH0Dkk1XwAIstmq.jpg",
        "https://nitter.net/pic/media%2FHH0Dk75XoAA79sG.jpg"
      ]
    },
    {
      "id": "ca264c0c56ecb098854e71473cbc1ab05bc4a4c2c7afcad158bf61d7dd61c5b0",
      "anime": "blackclover",
      "handle": "pacemanop",
      "sourceLabel": "Black Clover",
      "title": "#SD258 #SAKAMOTODAYS258 suzuki fucking delivered this chapter I’m really really convinced this fight has been a big upscale from gozu vs shishiba and it seems like tenkyu is still the same as before. ",
      "text": "#SD258 #SAKAMOTODAYS258 suzuki fucking delivered this chapter I’m really really convinced this fight has been a big upscale from gozu vs shishiba and it seems like tenkyu is still the same as before. the choreography just went straight up at the end thanks suzuki ; )",
      "url": "https://nitter.net/OkizemeSD/status/2052613004118618258#m",
      "date": "Fri, 08 May 2026 04:54:10 GMT",
      "isSpoiler": false,
      "hasAttachments": true,
      "attachments": [
        "https://nitter.net/pic/media%2FHHxYphnWIAIsWc3.jpg"
      ]
    }
  ]
}